odoo/addons/web_edit_user_filter/README.rst
odoo/addons/web_edit_user_filter/__init__.py
odoo/addons/web_edit_user_filter/__manifest__.py
odoo/addons/web_edit_user_filter/i18n/ca.po
odoo/addons/web_edit_user_filter/i18n/da.po
odoo/addons/web_edit_user_filter/i18n/es.po
odoo/addons/web_edit_user_filter/i18n/fr.po
odoo/addons/web_edit_user_filter/i18n/hr.po
odoo/addons/web_edit_user_filter/i18n/pt.po
odoo/addons/web_edit_user_filter/i18n/pt_BR.po
odoo/addons/web_edit_user_filter/i18n/tr.po
odoo/addons/web_edit_user_filter/i18n/web_edit_user_filter.pot
odoo/addons/web_edit_user_filter/i18n/zh_CN.po
odoo/addons/web_edit_user_filter/models/__init__.py
odoo/addons/web_edit_user_filter/models/ir_filters.py
odoo/addons/web_edit_user_filter/readme/CONTRIBUTORS.rst
odoo/addons/web_edit_user_filter/readme/DESCRIPTION.rst
odoo/addons/web_edit_user_filter/readme/ROADMAP.rst
odoo/addons/web_edit_user_filter/readme/USAGE.rst
odoo/addons/web_edit_user_filter/static/description/edit_facet.png
odoo/addons/web_edit_user_filter/static/description/icon.png
odoo/addons/web_edit_user_filter/static/description/index.html
odoo/addons/web_edit_user_filter/static/src/js/backend.js
odoo/addons/web_edit_user_filter/static/src/scss/backend.scss
odoo/addons/web_edit_user_filter/static/src/xml/backend.xml
odoo/addons/web_edit_user_filter/templates/assets.xml
odoo/addons/web_edit_user_filter/tests/__init__.py
odoo/addons/web_edit_user_filter/tests/test_edit_user_filter.py
odoo12_addon_web_edit_user_filter-12.0.1.1.0.dist-info/METADATA
odoo12_addon_web_edit_user_filter-12.0.1.1.0.dist-info/WHEEL
odoo12_addon_web_edit_user_filter-12.0.1.1.0.dist-info/top_level.txt
odoo12_addon_web_edit_user_filter-12.0.1.1.0.dist-info/RECORD
